<?xml version="1.0" encoding="utf-8"?>
<otrs_config version="1.0" init="Config">
    <CVS>$Id$</CVS>

    <ConfigItem Name="Notification::Transport###Email" Required="0" Valid="1">
        <Description Translatable="1">Defines all the parameters for this notification transport.</Description>
        <Group>Ticket</Group>
        <SubGroup>Frontend::Admin::AdminNotificationEvent</SubGroup>
        <Setting>
            <Hash>
                <Item Key="Module">Kernel::System::Ticket::Event::NotificationEvent::Transport::EmailX</Item>
                <Item Key="Name">Email</Item>
                <Item Key="Icon">fa fa-envelope</Item>
                <Item Key="Prio">100</Item>
                <Item Key="IsOTRSBusinessTransport">0</Item>
                <Item Key="AgentEnabledByDefault">1</Item>
            </Hash>
        </Setting>
    </ConfigItem>

    <ConfigItem Name="Notification::Transport###AgentOverlay" Required="0" Valid="1">
        <Description Translatable="1">Defines all the parameters for this notification transport.</Description>
        <Group>Ticket</Group>
        <SubGroup>Frontend::Admin::AdminNotificationEvent</SubGroup>
        <Setting>
            <Hash>
                <Item Key="Module">Kernel::System::Ticket::Event::NotificationEvent::Transport::AgentOverlay</Item>
                <Item Key="Name">Agent Notification (Popup/Dashboard)</Item>
                <Item Key="Icon">fa fa-th-list</Item>
                <Item Key="Prio">110</Item>
                <Item Key="IsOTRSBusinessTransport">0</Item>
                <Item Key="AgentEnabledByDefault">0</Item>
            </Hash>
        </Setting>
    </ConfigItem>
    <ConfigItem Name="PreApplicationModule###AgentOverlayPopup" Required="0" Valid="1">
        <Description Translatable="1">This module creates popus for notifications.</Description>
        <Group>Ticket</Group>
        <SubGroup>Core::Ticket</SubGroup>
        <Setting>
            <String Regex="">Kernel::Modules::AgentOverlayPopup</String>
        </Setting>
    </ConfigItem>
    <ConfigItem Name="DashboardBackend###0560-AgentOverlay" Required="0" Valid="1">
        <Description Translatable="1">Parameters for the dashboard backend of the ticket calendar of the agent interface. "Limit" is the number of entries shown by default. "Group" is used to restrict the access to the plugin (e. g. Group: admin;group1;group2;). "Default" determines if the plugin is enabled by default or if the user needs to enable it manually. "CacheTTLLocal" is the cache time in minutes for the plugin.</Description>
        <Group>Ticket</Group>
        <SubGroup>Frontend::Agent::Dashboard</SubGroup>
        <Setting>
            <Hash>
                <Item Key="Module">Kernel::Output::HTML::Dashboard::AgentOverlay</Item>
                <Item Key="Title" Translatable="1">Agent Notifications</Item>
                <Item Key="Permission">rw</Item>
                <Item Key="OwnerOnly"></Item>
                <Item Key="Block">ContentSmall</Item>
                <Item Key="Group"></Item>
                <Item Key="Default">1</Item>
            </Hash>
        </Setting>
    </ConfigItem>

    <ConfigItem Name="Notification::Transport###NotificationView" Required="0" Valid="0">
        <Description Translatable="1">Defines all the parameters for this notification transport.</Description>
        <Group>Ticket</Group>
        <SubGroup>Frontend::Admin::AdminNotificationEvent</SubGroup>
        <Setting>
            <Hash>
                <Item Key="Module">Kernel::System::Ticket::Event::NotificationEvent::Transport::NotificationView</Item>
                <Item Key="Name">Web View</Item>
                <Item Key="Icon">fa fa-th-list</Item>
                <Item Key="Prio">110</Item>
                <Item Key="IsOTRSBusinessTransport">1</Item>
                <Item Key="AgentEnabledByDefault">0</Item>
            </Hash>
        </Setting>
    </ConfigItem>
    <ConfigItem Name="Notification::Transport###SMS" Required="0" Valid="0">
        <Description Translatable="1">Defines all the parameters for this notification transport.</Description>
        <Group>Ticket</Group>
        <SubGroup>Frontend::Admin::AdminNotificationEvent</SubGroup>
        <Setting>
            <Hash>
                <Item Key="Module">Kernel::System::Ticket::Event::NotificationEvent::Transport::SMS</Item>
                <Item Key="Name">SMS (Short Message Service)</Item>
                <Item Key="Icon">fa fa-mobile</Item>
                <Item Key="Prio">120</Item>
                <Item Key="IsOTRSBusinessTransport">1</Item>
                <Item Key="AgentEnabledByDefault">0</Item>
            </Hash>
        </Setting>
    </ConfigItem>
</otrs_config>
